copyable/__init__.py
copyable/core/__init__.py
copyable/tests/__init__.py
copyable/tests/test_0.py
copyable/tests/test_1.py
copyable-1.0.0.dist-info/licenses/LICENSE.txt
copyable-1.0.0.dist-info/METADATA
copyable-1.0.0.dist-info/WHEEL
copyable-1.0.0.dist-info/top_level.txt
copyable-1.0.0.dist-info/RECORD
