Metadata-Version: 2.4
Name: copyable
Version: 1.0.0
Summary: This project provides a copyable ABC.
Author-email: Johannes <johannes.programming@gmail.com>
License: The MIT License (MIT)
Project-URL: Download, https://pypi.org/project/copyable/#files
Project-URL: Index, https://pypi.org/project/copyable/
Project-URL: Source, https://github.com/johannes-programming/copyable/
Project-URL: Website, https://copyable.johannes-programming.online/
Classifier: Development Status :: 5 - Production/Stable
Classifier: License :: OSI Approved :: MIT License
Classifier: Natural Language :: English
Classifier: Operating System :: OS Independent
Classifier: Programming Language :: Python
Classifier: Programming Language :: Python :: 3
Classifier: Programming Language :: Python :: 3 :: Only
Classifier: Typing :: Typed
Requires-Python: >=3.11
License-File: LICENSE.txt
Requires-Dist: setdoc<2,>=1.2.7
Dynamic: license-file
